statelint/__init__.py
statelint/__main__.py
statelint/cli.py
statelint/config.py
statelint/linter.py
statelint/fields/__init__.py
statelint/fields/any_field.py
statelint/fields/base.py
statelint/fields/bool_field.py
statelint/fields/common.py
statelint/fields/container.py
statelint/fields/field_value.py
statelint/fields/jsonata_field.py
statelint/fields/list_field.py
statelint/fields/num_field.py
statelint/fields/object_field.py
statelint/fields/pattern_field.py
statelint/fields/str_field.py
statelint/fields/timestamp_field.py
statelint/nodes/__init__.py
statelint/nodes/choice_state.py
statelint/nodes/container_state.py
statelint/nodes/fail_state.py
statelint/nodes/map_state.py
statelint/nodes/node.py
statelint/nodes/parallel_state.py
statelint/nodes/pass_state.py
statelint/nodes/state.py
statelint/nodes/state_machine.py
statelint/nodes/succeed_state.py
statelint/nodes/task_state.py
statelint/nodes/unknown_state.py
statelint/nodes/wait_state.py
statelint/nodes/factory/__init__.py
statelint/nodes/factory/factory.py
statelint/nodes/mixins/__init__.py
statelint/nodes/mixins/arguments_mixin.py
statelint/nodes/mixins/assign_mixin.py
statelint/nodes/mixins/catch_mixin.py
statelint/nodes/mixins/choices_mixin.py
statelint/nodes/mixins/output_mixin.py
statelint/nodes/mixins/payload_template_mixin.py
statelint/nodes/mixins/result_path_mixin.py
statelint/nodes/mixins/retrier_mixin.py
statelint/problem/__init__.py
statelint/problem/predicate.py
statelint/problem/problem.py
statelint/problem/problem_type.py
statelint/utils/__init__.py
statelint/utils/jsonata_helper.py
statelint/utils/re_helper.py
statelint-3.1.0.dist-info/licenses/LICENSE
statelint-3.1.0.dist-info/METADATA
statelint-3.1.0.dist-info/WHEEL
statelint-3.1.0.dist-info/entry_points.txt
statelint-3.1.0.dist-info/top_level.txt
statelint-3.1.0.dist-info/RECORD
