Metadata-Version: 2.4
Name: statelint
Version: 3.1.0
Summary: command-line validator for Amazon States Language
Home-page: https://github.com/taro-kayo/statelint
Author: taro-kayo
License: Apache License 2.0
Classifier: Development Status :: 5 - Production/Stable
Classifier: Environment :: Console
Classifier: Intended Audience :: Developers
Classifier: Programming Language :: Python
Classifier: Programming Language :: Python :: 3
Classifier: Programming Language :: Python :: 3 :: Only
Classifier: Programming Language :: Python :: 3.10
Classifier: Programming Language :: Python :: 3.11
Classifier: Programming Language :: Python :: 3.12
Classifier: Programming Language :: Python :: 3.13
Classifier: Programming Language :: Python :: 3.14
Requires-Python: >=3.10.0
License-File: LICENSE
Requires-Dist: python-dateutil>=2.8.2
Requires-Dist: regex>=2023.5.5
Provides-Extra: yaml
Requires-Dist: PyYAML>=6.0; extra == "yaml"
Provides-Extra: jsonata
Requires-Dist: jsonata-python>=0.6.0; extra == "jsonata"
Dynamic: license-file
